CHANGES.rst
MANIFEST.in
README.rst
setup.cfg
setup.py
tox.ini
version.txt
src/metapensiero/__init__.py
src/metapensiero.reactive.egg-info/PKG-INFO
src/metapensiero.reactive.egg-info/SOURCES.txt
src/metapensiero.reactive.egg-info/dependency_links.txt
src/metapensiero.reactive.egg-info/namespace_packages.txt
src/metapensiero.reactive.egg-info/pbr.json
src/metapensiero.reactive.egg-info/requires.txt
src/metapensiero.reactive.egg-info/top_level.txt
src/metapensiero/reactive/__init__.py
src/metapensiero/reactive/computation.py
src/metapensiero/reactive/dependency.py
src/metapensiero/reactive/exception.py
src/metapensiero/reactive/nlist.py
src/metapensiero/reactive/tracker.py
src/metapensiero/reactive/value.py
src/metapensiero/reactive/flush/__init__.py
src/metapensiero/reactive/flush/asyncio.py
src/metapensiero/reactive/flush/base.py
src/metapensiero/reactive/flush/gevent.py