Metadata-Version: 1.1
Name: metapensiero.reactive
Version: 0.6
Summary: an unobtrusive and light reactive system
Home-page: https://github.com/azazel75/metapensiero.reactive
Author: Alberto Berti
Author-email: alberto@metapensiero.it
License: GPLv3+
Keywords: reactive functional dataflow asyncio gevent
Platform: UNKNOWN
Classifier: Development Status :: 5 - Production/Stable
Classifier: Programming Language :: Python
Classifier: Programming Language :: Python :: 2
Classifier: Programming Language :: Python :: 2.7
Classifier: Programming Language :: Python :: 3
Classifier: Programming Language :: Python :: 3.4
Classifier: Programming Language :: Python :: 3.5
Classifier: Intended Audience :: Developers
Classifier: License :: OSI Approved :: GNU General Public License (GPL)
